cosmo_geff-0.1.1.dist-info/licenses/LICENSE
geff/__init__.py
geff/bgtypes.py
geff/gef.py
geff/mbm.py
geff/solver.py
geff/_docs/__init__.py
geff/_docs/docs_bgtypes.py
geff/_docs/docs_gef.py
geff/_docs/docs_gw.py
geff/_docs/docs_mbm.py
geff/_docs/docs_models.py
geff/_docs/docs_pt.py
geff/_docs/docs_solver.py
geff/data/eff_dof.dat
geff/models/__init__.py
geff/models/fai_basic.py
geff/models/fai_kh.py
geff/models/pai.py
geff/tools/__init__.py
geff/tools/gw.py
geff/tools/pt.py
geff/utility/__init__.py
geff/utility/boundary.py
geff/utility/cosmo.py
geff/utility/eom.py
geff/utility/general.py
geff/utility/mode.py
cosmo_geff-0.1.1.dist-info/METADATA
cosmo_geff-0.1.1.dist-info/WHEEL
cosmo_geff-0.1.1.dist-info/top_level.txt
cosmo_geff-0.1.1.dist-info/RECORD
