Metadata-Version: 2.4
Name: cosmo-geff
Version: 0.1.1
Summary: The GEFF allows simulating gauge-field production during inflation using the gradient expansion formalism.
Author-email: Richard von Eckardstein <richard.voneckardstein@uni-muenster.de>
License: 
Project-URL: Homepage, https://richard-von-eckardstein.github.io/GEFF/geff.html
Project-URL: Repository, https://github.com/richard-von-eckardstein/GEFF
Project-URL: Changelog, https://github.com/richard-von-eckardstein/GEFF/blob/main/CHANGELOG.md
Keywords: geff,inflation,cosmology
Classifier: Development Status :: 4 - Beta
Classifier: Intended Audience :: Science/Research
Classifier: Natural Language :: English
Classifier: Programming Language :: Python :: 3
Classifier: Topic :: Scientific/Engineering :: Physics
Requires-Python: >=3.10
License-File: LICENSE
Requires-Dist: scipy>=1.15.0
Requires-Dist: numpy>=2.2.6
Requires-Dist: pandas>=2.3.0
Requires-Dist: tabulate
Requires-Dist: mpmath>=1.3
Requires-Dist: natpy
Dynamic: license-file
